ioregistry/__init__.py
ioregistry/_version.py
ioregistry/allocated.py
ioregistry/exceptions.py
ioregistry/ioentry.py
ioregistry/native/__init__.py
ioregistry/native/core_foundation.py
ioregistry/native/iokit.py
ioregistry-0.0.4.dist-info/LICENSE
ioregistry-0.0.4.dist-info/METADATA
ioregistry-0.0.4.dist-info/WHEEL
ioregistry-0.0.4.dist-info/top_level.txt
ioregistry-0.0.4.dist-info/RECORD
